{
  "schemaVersion": 1,
  "cardId": "esw2_dbg__ocr_024",
  "source": {
    "draft": "data/import/card-drafts/esw2_dbg__ocr_024.json",
    "image": "assets/cards/raw/1000009232.jpg",
    "ocrText": "data/import/card-texts/esw2_dbg__ocr_024.md"
  },
  "visible": {
    "nameRu": "Вялая палочка",
    "cost": 0,
    "victoryPoints": -1,
    "typeRu": null,
    "cardKind": "limpWand",
    "cardTypes": [],
    "textRu": "(Эффекта нет.)",
    "markers": [],
    "uncertainty": [
      "OCR указал, что видимый тип карты не виден или не указан на видимой части."
    ]
  },
  "engine": {
    "runtimeSchema": "krutagidon.cardDefinition.v0",
    "mappingStatus": "supported",
    "playableInV0": true,
    "needsEffectMapping": false,
    "cardKind": "limpWand",
    "cardTypes": [],
    "cost": 0,
    "victoryPoints": -1,
    "isOngoing": false,
    "marketChipMarker": false,
    "effects": [],
    "unsupportedMechanics": []
  }
}
